gpdf/__init__.py
gpdf-0.1.0.dist-info/LICENSE
gpdf-0.1.0.dist-info/METADATA
gpdf-0.1.0.dist-info/WHEEL
gpdf-0.1.0.dist-info/top_level.txt
gpdf-0.1.0.dist-info/RECORD
